semestralka1/kouba_tadeas_CPU.v
`default_nettype none
//=========================================================================================
//=========================================================================================
//                 CPU
//=========================================================================================
//=========================================================================================
module processor( input         clk, reset, //
                  output [31:0] PC, //
                  input  [31:0] instruction, //
                  output        WE, //
                  output unsigned [31:0] address_to_mem, //
                  output unsigned [31:0] data_to_mem, //
                  input  [31:0] data_from_mem //
                );
    
    wire ALUSrc; // 0/1 Which source to use for SrcB
    wire [3:0] AluControl; // 0-7 which operation should ALU make
    wire MemWrite; // 0/1 Write to memory?
    wire MemToReg; // 0/1 Which source to use for registerSet write
    wire RegWrite; // 0/1 Write to register?
    wire BranchBeq; // 0/1 Branch?
    wire BranchJal; // 0/1 Jump? 
    wire BranchJalr; // 0/1 Return?
    wire [2:0] immControl; // 0-7 Controls how immDecode decodes imm

    wire [31:0] ImmOp; // return value of immDecode
    wire [31:0] res; // Value to write to register
    wire [31:0] Reg1; // Value from register1
    wire [31:0] Reg2; // Value from register2
   
    wire [31:0] SrcB; // Operand2 of ALU (Decided by ALUSrc - can be ImmOp or Reg2)

    wire [31:0] ALUout; // Output of ALU
    wire Zero; // 1 if ALUout == 0 else 1
    wire [31:0] branchTarget;
    reg BranchJalx;
    reg BranchOutcome;
    wire [31:0] brJalxMuxOut;
    wire [31:0] PCn;

    wire [31:0] data;
    wire [31:0] pc;
    wire [31:0] PCPlus4;
    wire [31:0] ImmOpPlusPC;
    wire [31:0] SrcA;

    assign PCPlus4 = pc + 4;
    assign ImmOpPlusPC = ImmOp + pc;
    assign SrcA = Reg1; // Operand1 of ALU 
    assign data = data_from_mem;

    always @(*)
    begin
        BranchJalx = BranchJal || BranchJalr;
        BranchOutcome = (BranchBeq && Zero) || BranchJalx;
    end


    CTRL_unit ctrl(instruction[6:0], instruction[31:25], 
                   instruction[14:12],
                   ALUSrc, AluControl, MemWrite, MemToReg, RegWrite, BranchBeq,
                   BranchJal, BranchJalr, immControl
                   );
    
    immDecode immDec(instruction[31:0],
                       immControl,
                       ImmOp);

    registerSet registers(instruction[19:15], 
                          instruction[24:20],
                          instruction[11:7],
                          clk, reset, RegWrite,
                          res, Reg1, Reg2);
    
    ALU alu(AluControl, pc, SrcA, SrcB, ALUout, Zero);
    
    register PCRegister(PCn, clk, reset, pc);
    
    mux2_1 aluMux(Reg2, ImmOp, ALUSrc, SrcB);
    
    mux2_1 brTargetMux( ImmOpPlusPC,ALUout,BranchJalr,branchTarget);

    mux2_1 brJalxMux(ALUout, PCPlus4, BranchJalx, brJalxMuxOut );
    
    mux2_1 dataMemMux( brJalxMuxOut, data, MemToReg, res);

    mux2_1 PCMux(PCPlus4, branchTarget, BranchOutcome, PCn);


    assign PC = pc;
    assign WE = MemWrite;
    assign address_to_mem = ALUout;
    assign data_to_mem = Reg2;

endmodule
//=========================================================================================
//=========================================================================================
//                 ARITHMETIC AND LOGIC UNIT
//=========================================================================================
//=========================================================================================
module ALU( input [3:0] ALUControl,
            input [31:0] pc,
            input signed [31:0] SrcA, SrcB,
            output reg [31:0] ALUout, 
            output reg Zero
          );

// ALUControl
// 0000 = +
// 0001 = &
// 0010 = -
// 0011 = <
// 0100 = /
// 0101 = %
// 0110 = !<
// 0111 = LUI
// 1000 = <<
// 1001 = >>    
// 1010 = auipc


    always @(*)
    begin
        case (ALUControl)
            0: ALUout = SrcA + SrcB;
            1: ALUout = SrcA & SrcB;
            2: ALUout = SrcA - SrcB;
            3: ALUout = SrcA < SrcB;
            4: ALUout = SrcA / SrcB;
            5: ALUout = SrcA % SrcB;
            6: ALUout = !(SrcA < SrcB);
            7: ALUout = {SrcB[31:12], 12'b0};
            8: ALUout = SrcA << SrcB;
            9: ALUout = SrcA >> SrcB;
            10: ALUout = pc + {SrcB[31:12], 12'b0};
            default:;
        endcase
    end

    always @(ALUout)
    begin
        if (ALUout==0)
            Zero = 1;
        else
            Zero = 0;
    end
endmodule
//=========================================================================================
//=========================================================================================
//                 IMMIDIATE CONTROL
//=========================================================================================
//=========================================================================================
module immDecode(input [31:0] inst, // value of instruction[31:0]
                  input [2:0] control,
                  output reg [31:0] immOp
                 );
// immControl
// 000 I-Type
// 001 S-Type
// 010 B-Type
// 011 J-Type
// 100 U-Type


    always @(*)
    begin
        case(control)
            0: immOp = { {20{inst[31]}}, inst[31:20]}; // I
            1: immOp = { {20{inst[31]}}, inst[31:25], inst[11:7]}; // S
            2: immOp = { {20{inst[31]}}, inst[7], inst[30:25], inst[11:8], 1'b0}; // B
            3: immOp = { {12{inst[31]}}, inst[19:12], inst[20], inst[30:21],1'b0}; // J
            4: immOp = { inst[31:12], 12'b0}; // U
            default:;
        endcase
    end

endmodule
//=========================================================================================
//=========================================================================================
//                 CONTROL UNIT       
//=========================================================================================
//=========================================================================================
module CTRL_unit( input [6:0] opCode, funct7,
                  input [2:0] funct3,
                  output ALUSrc,
                  output [3:0] ALUControl,
                  output MemWrite,
                  output MemToReg,
                  output RegWrite,
                  output BranchBeq,
                  output BranchJal,
                  output BranchJalr,
                  output [2:0] immControl
                );
    reg [13:0] out; // output bits in order of module arguments

// ALUControl
// 0000 = +    // immControl
// 0001 = &    // 000 I-Type
// 0010 = -    // 001 S-Type
// 0011 = <    // 010 B-Type
// 0100 = /    // 011 J-Type
// 0101 = %    // 100 U-Type
// 0110 = !<   // 111 R-Type
// 0111 = LUI
// 1000 = <<
// 1001 = >>    
// 1010 = auipc

    always @(*)
    begin
        casez ({opCode,funct7,funct3})
            'b0110011_0000000_000: out = 'b0_0000_0_0_1_0_0_0_111;   // add

            'b0010011_???????_000: out = 'b1_0000_0_0_1_0_0_0_000;   // addi

            'b0110011_0000000_111: out = 'b0_0001_0_0_1_0_0_0_111;   // and
            'b0110011_0100000_000: out = 'b0_0010_0_0_1_0_0_0_111;   // sub
            'b0110011_0000000_010: out = 'b0_0011_0_0_1_0_0_0_111;   // slt
            'b0110011_0000001_100: out = 'b0_0100_0_0_1_0_0_0_111;   // div
            'b0110011_0000001_110: out = 'b0_0101_0_0_1_0_0_0_111;   // rem
            'b0110011_0000000_001: out = 'b0_1000_0_0_1_0_0_0_111;   // sll           
            'b0110011_0000000_101: out = 'b0_1001_0_0_1_0_0_0_111;   // srl           
            'b0110011_0100000_101: out = 'b0_1001_0_0_1_0_0_0_111;   // sra           

            'b1100011_???????_000: out = 'b0_0010_0_0_0_1_0_0_010;   // beq
            'b1100011_???????_100: out = 'b0_0110_0_0_0_1_0_0_010;   // blt

            'b0000011_???????_010: out = 'b1_0000_0_1_1_0_0_0_000;   // lw
            'b0100011_???????_010: out = 'b1_0000_1_0_0_0_0_0_001;   // sw

            'b0110111_???????_???: out = 'b1_0111_0_0_1_0_0_0_100;   // lui
            'b0010111_???????_???: out = 'b1_1010_0_0_1_0_0_0_100;   // auipc

            'b1101111_???????_???: out = 'b0_0000_0_0_1_0_1_0_011;   // jal
            'b1100111_???????_000: out = 'b1_0000_0_0_1_0_0_1_000;   // jalr
            
            default:;
        endcase
    end

    assign ALUSrc = out[13];
    assign ALUControl = out[12:9];
    assign MemWrite = out[8];
    assign MemToReg = out[7];
    assign RegWrite = out[6];
    assign BranchBeq = out[5];
    assign BranchJal = out[4];
    assign BranchJalr = out[3];
    assign immControl = out[2:0];

endmodule
//=========================================================================================
//=========================================================================================
//                 Multiplexer 2 to 1
//=========================================================================================
//=========================================================================================
module mux2_1(	input [31:0] a,b, 
                input select,
		output reg [31:0] y);

	always@(*)
    begin
		if (select==0) y <= a;
		else y <= b;
    end

endmodule
//=========================================================================================
//=========================================================================================
//                 REGISTER SET
//=========================================================================================
//=========================================================================================
module registerSet ( input [4:0] A1, A2, A3,
                     input clk, reset, WE3,
                     input [31:0] WD3,
                     output [31:0] RD1, RD2
                    );

    reg [31:0] rf[31:0];
    // wire zero = 0;

    integer i;
    always @(posedge clk or reset)
    begin
        if ( reset == 1 )
            for (i = 0; i <= 31 ; i=i+1)
            begin
                rf[i] = 0;    
            end
    end

    always @(posedge clk)
    begin
        if (WE3)
            if (A3 != 0)
                rf[A3] = WD3;
            else;
        else;
    end
  
    assign RD1 = rf[A1];
    assign RD2 = rf[A2];


endmodule
//=========================================================================================
//=========================================================================================
//                 PC REGISTER
//=========================================================================================
//=========================================================================================
module register(input [31:0] in,
            input clk, reset,
            output reg [31:0] out);
    
    always @(posedge clk or reset)
    begin
        if (reset==1)
            out <= 0;
        else
            out <= in;
    end
endmodule
//=========================================================================================
//=========================================================================================
//                 END OF FILE
//=========================================================================================
//=========================================================================================

`default_nettype wire

semestralka1/supportModules.v
module top (	input         clk, reset,
		output [31:0] data_to_mem, address_to_mem,
		output        write_enable);

	wire [31:0] pc, instruction, data_from_mem;

	inst_mem  imem(pc[7:2], instruction);
	data_mem  dmem(clk, write_enable, address_to_mem, data_to_mem, data_from_mem);
	processor CPU(clk, reset, pc, instruction, write_enable, address_to_mem, data_to_mem, data_from_mem);
endmodule

//-------------------------------------------------------------------
module data_mem (input clk, we,
		 input  [31:0] address, wd,
		 output [31:0] rd);

	reg [31:0] RAM[63:0];

	initial begin
		$readmemh ("memfile_data.hex",RAM,0,63);
	end

	assign rd=RAM[address[31:2]]; // word aligned

	always @ (posedge clk)
		if (we)
			RAM[address[31:2]]<=wd;
endmodule

//-------------------------------------------------------------------
module inst_mem (input  [5:0]  address,
		 output [31:0] rd);

	reg [31:0] RAM[63:0];
	initial begin
		$readmemh ("memfile_inst.hex",RAM,0,63);
	end
	assign rd=RAM[address]; // word aligned
endmodule

semestralka1/sim_CPU.v
module testbench();
	reg         clk;
	reg         reset;
	wire [31:0] data_to_mem, address_to_mem;
	wire        write_enable;

	top simulated_system (clk, reset, data_to_mem, address_to_mem, write_enable);

	initial	begin
		$dumpfile("test");
		$dumpvars;
		reset<=1; # 2; reset<=0;
		#100;
		$writememh ("memfile_data_after_simulation.hex",simulated_system.dmem.RAM,0,63);
		$finish;
	end

	// generate clock
	always	begin
		clk<=1; # 1; clk<=0; # 1;
	end
endmodule

semestralka1/test.vcd
$date
	Fri Nov 11 15:09:14 2022
$end
$version
	Icarus Verilog
$end
$timescale
	1s
$end
$scope module testbench $end
$var wire 1 ! write_enable $end
$var wire 32 " data_to_mem [31:0] $end
$var wire 32 # address_to_mem [31:0] $end
$var reg 1 $ clk $end
$var reg 1 % reset $end
$scope module simulated_system $end
$var wire 1 $ clk $end
$var wire 1 % reset $end
$var wire 1 ! write_enable $end
$var wire 32 & pc [31:0] $end
$var wire 32 ' instruction [31:0] $end
$var wire 32 ( data_to_mem [31:0] $end
$var wire 32 ) data_from_mem [31:0] $end
$var wire 32 * address_to_mem [31:0] $end
$scope module CPU $end
$var wire 32 + PC [31:0] $end
$var wire 32 , SrcA [31:0] $end
$var wire 1 ! WE $end
$var wire 32 - address_to_mem [31:0] $end
$var wire 1 $ clk $end
$var wire 32 . data [31:0] $end
$var wire 32 / data_to_mem [31:0] $end
$var wire 1 % reset $end
$var wire 32 0 res [31:0] $end
$var wire 32 1 pc [31:0] $end
$var wire 32 2 instruction [31:0] $end
$var wire 3 3 immControl [2:0] $end
$var wire 32 4 data_from_mem [31:0] $end
$var wire 32 5 branchTarget [31:0] $end
$var wire 32 6 brJalxMuxOut [31:0] $end
$var wire 1 7 Zero $end
$var wire 32 8 SrcB [31:0] $end
$var wire 1 9 RegWrite $end
$var wire 32 : Reg2 [31:0] $end
$var wire 32 ; Reg1 [31:0] $end
$var wire 32 < PCn [31:0] $end
$var wire 32 = PCPlus4 [31:0] $end
$var wire 1 > MemWrite $end
$var wire 1 ? MemToReg $end
$var wire 32 @ ImmOpPlusPC [31:0] $end
$var wire 32 A ImmOp [31:0] $end
$var wire 1 B BranchJalr $end
$var wire 1 C BranchJal $end
$var wire 1 D BranchBeq $end
$var wire 4 E AluControl [3:0] $end
$var wire 32 F ALUout [31:0] $end
$var wire 1 G ALUSrc $end
$var reg 1 H BranchJalx $end
$var reg 1 I BranchOutcome $end
$scope module PCMux $end
$var wire 32 J a [31:0] $end
$var wire 1 I select $end
$var wire 32 K b [31:0] $end
$var reg 32 L y [31:0] $end
$upscope $end
$scope module PCRegister $end
$var wire 1 $ clk $end
$var wire 32 M in [31:0] $end
$var wire 1 % reset $end
$var reg 32 N out [31:0] $end
$upscope $end
$scope module alu $end
$var wire 32 O SrcA [31:0] $end
$var wire 32 P pc [31:0] $end
$var wire 32 Q SrcB [31:0] $end
$var wire 4 R ALUControl [3:0] $end
$var reg 32 S ALUout [31:0] $end
$var reg 1 7 Zero $end
$upscope $end
$scope module aluMux $end
$var wire 1 G select $end
$var wire 32 T b [31:0] $end
$var wire 32 U a [31:0] $end
$var reg 32 V y [31:0] $end
$upscope $end
$scope module brJalxMux $end
$var wire 32 W a [31:0] $end
$var wire 32 X b [31:0] $end
$var wire 1 H select $end
$var reg 32 Y y [31:0] $end
$upscope $end
$scope module brTargetMux $end
$var wire 32 Z a [31:0] $end
$var wire 32 [ b [31:0] $end
$var wire 1 B select $end
$var reg 32 \ y [31:0] $end
$upscope $end
$scope module ctrl $end
$var wire 3 ] funct3 [2:0] $end
$var wire 7 ^ funct7 [6:0] $end
$var wire 7 _ opCode [6:0] $end
$var wire 3 ` immControl [2:0] $end
$var wire 1 9 RegWrite $end
$var wire 1 > MemWrite $end
$var wire 1 ? MemToReg $end
$var wire 1 B BranchJalr $end
$var wire 1 C BranchJal $end
$var wire 1 D BranchBeq $end
$var wire 1 G ALUSrc $end
$var wire 4 a ALUControl [3:0] $end
$var reg 14 b out [13:0] $end
$upscope $end
$scope module dataMemMux $end
$var wire 32 c a [31:0] $end
$var wire 32 d b [31:0] $end
$var wire 1 ? select $end
$var reg 32 e y [31:0] $end
$upscope $end
$scope module immDec $end
$var wire 3 f control [2:0] $end
$var wire 32 g inst [31:0] $end
$var reg 32 h immOp [31:0] $end
$upscope $end
$scope module registers $end
$var wire 5 i A1 [4:0] $end
$var wire 5 j A2 [4:0] $end
$var wire 5 k A3 [4:0] $end
$var wire 32 l RD1 [31:0] $end
$var wire 32 m RD2 [31:0] $end
$var wire 32 n WD3 [31:0] $end
$var wire 1 9 WE3 $end
$var wire 1 $ clk $end
$var wire 1 % reset $end
$var integer 32 o i [31:0] $end
$upscope $end
$upscope $end
$scope module dmem $end
$var wire 32 p address [31:0] $end
$var wire 1 $ clk $end
$var wire 32 q rd [31:0] $end
$var wire 32 r wd [31:0] $end
$var wire 1 ! we $end
$upscope $end
$scope module imem $end
$var wire 6 s address [5:0] $end
$var wire 32 t rd [31:0] $end
$upscope $end
$upscope $end
$upscope $end
$enddefinitions $end
#0
$dumpvars
b100000000000010110010011 t
b0 s
b0 r
b101 q
b1000 p
b100000 o
b1000 n
b0 m
b0 l
b1011 k
b1000 j
b0 i
b1000 h
b100000000000010110010011 g
b0 f
b1000 e
b101 d
b1000 c
b10000001000000 b
b0 a
b0 `
b10011 _
b0 ^
b0 ]
b1000 \
b1000 [
b1000 Z
b1000 Y
b100 X
b1000 W
b1000 V
b0 U
b1000 T
b1000 S
b0 R
b1000 Q
b0 P
b0 O
b0 N
b100 M
b100 L
b1000 K
b100 J
0I
0H
1G
b1000 F
b0 E
0D
0C
0B
b1000 A
b1000 @
0?
0>
b100 =
b100 <
b0 ;
b0 :
19
b1000 8
07
b1000 6
b1000 5
b101 4
b0 3
b100000000000010110010011 2
b0 1
b1000 0
b0 /
b101 .
b1000 -
b0 ,
b0 +
b1000 *
b101 )
b0 (
b100000000000010110010011 '
b0 &
1%
1$
b1000 #
b0 "
0!
$end
#1
0$
#2
b101 0
b101 e
b101 n
b1000 6
b1000 Y
b1000 c
b0 8
b0 Q
b0 V
b100 5
b100 K
b100 \
b1000 <
b1000 L
b1000 M
b101 .
b101 d
b101 )
b101 4
b101 q
1?
b1000 #
b1000 *
b1000 -
b1000 p
b1000 F
b1000 S
b1000 W
b1000 [
b10000011000000 b
b0 j
b1000 ,
b1000 O
b1000 ;
b1000 l
b1011 i
b10 ]
b11 _
b0 A
b0 T
b0 h
b1011010010110000011 '
b1011010010110000011 2
b1011010010110000011 g
b1011010010110000011 t
b1 s
b100 @
b100 Z
b1000 =
b1000 J
b1000 X
b100 &
b100 +
b100 1
b100 N
b100 P
1$
0%
#3
0$
#4
b1000 5
b1000 K
b1000 \
b1100 <
b1100 L
b1100 M
17
0?
b10000001000000 b
b1100 k
b0 i
b0 ]
b10011 _
b11000010011 '
b11000010011 2
b11000010011 g
b11000010011 t
b10 s
b0 0
b0 e
b0 n
b0 6
b0 Y
b0 c
b1000 @
b1000 Z
b1100 =
b1100 J
b1100 X
b1000 &
b1000 +
b1000 1
b1000 N
b1000 P
b0 .
b0 d
b0 )
b0 4
b0 q
b0 #
b0 *
b0 -
b0 p
b0 F
b0 S
b0 W
b0 [
b0 ,
b0 O
b0 ;
b0 l
1$
#5
0$
#6
b1100 5
b1100 K
b1100 \
b10000 <
b10000 L
b10000 M
b1010 k
b10100010011 '
b10100010011 2
b10100010011 g
b10100010011 t
b11 s
b1100 @
b1100 Z
b10000 =
b10000 J
b10000 X
b1100 &
b1100 +
b1100 1
b1100 N
b1100 P
1$
#7
0$
#8
b10000 5
b10000 K
b10000 \
b10100 <
b10100 L
b10100 M
1?
b10000011000000 b
b1011 k
b10 ]
b11 _
b10010110000011 '
b10010110000011 2
b10010110000011 g
b10010110000011 t
b100 s
b10000 @
b10000 Z
b10100 =
b10100 J
b10100 X
b10000 &
b10000 +
b10000 1
b10000 N
b10000 P
1$
#9
0$
#10
b10100 0
b10100 e
b10100 n
b100 6
b100 Y
b100 c
07
b10100 .
b10100 d
b10100 )
b10100 4
b10100 q
b100 #
b100 *
b100 -
b100 p
b100 F
b100 S
b100 W
b100 [
b100 8
b100 Q
b100 V
b11000 5
b11000 K
b11000 \
b11000 <
b11000 L
b11000 M
b1100 k
b100 j
b100 A
b100 T
b100 h
b10000000010011000000011 '
b10000000010011000000011 2
b10000000010011000000011 g
b10000000010011000000011 t
b101 s
b11000 @
b11000 Z
b11000 =
b11000 J
b11000 X
b10100 &
b10100 +
b10100 1
b10100 N
b10100 P
1$
#11
0$
#12
b10100 6
b10100 Y
b10100 c
b1001 .
b1001 d
b1001 )
b1001 4
b1001 q
b10100 #
b10100 *
b10100 -
b10100 p
b10100 F
b10100 S
b10100 W
b10100 [
b10100 0
b10100 e
b10100 n
b10100 8
b10100 Q
b10100 V
b100100 5
b100100 K
b100100 \
b11100 <
b11100 L
b11100 M
0G
0?
b111 3
b111 `
b111 f
b1000111 b
b1101 k
b10100 "
b10100 (
b10100 /
b10100 r
b10100 :
b10100 U
b10100 m
b1100 j
b1011 i
b0 ]
b110011 _
b1100 A
b1100 T
b1100 h
b110001011000011010110011 '
b110001011000011010110011 2
b110001011000011010110011 g
b110001011000011010110011 t
b110 s
b100100 @
b100100 Z
b11100 =
b11100 J
b11100 X
b11000 &
b11000 +
b11000 1
b11000 N
b11000 P
1$
#13
0$
#14
b11100 0
b11100 e
b11100 n
b11100 6
b11100 Y
b11100 c
b0 8
b0 Q
b0 V
b11100 5
b11100 K
b11100 \
b100000 <
b100000 L
b100000 M
b10 .
b10 d
b10 )
b10 4
b10 q
b11100 #
b11100 *
b11100 -
b11100 p
b11100 F
b11100 S
b11100 W
b11100 [
b0 A
b0 T
b0 h
1G
b1010 E
b1010 R
b1010 a
b100 3
b100 `
b100 f
b11010001000100 b
b110 k
b0 "
b0 (
b0 /
b0 r
b0 :
b0 U
b0 m
b0 j
b0 i
b10111 _
b1100010111 '
b1100010111 2
b1100010111 g
b1100010111 t
b111 s
b11100 @
b11100 Z
b100000 =
b100000 J
b100000 X
b11100 &
b11100 +
b11100 1
b11100 N
b11100 P
1$
#15
0$
#16
b100100 0
b100100 e
b100100 n
b10011100 8
b10011100 Q
b10011100 V
b100100 6
b100100 Y
b100100 c
b10111000 5
b10111000 K
b10111000 \
b10111000 <
b10111000 L
b10111000 M
1I
1H
b0 E
b0 R
b0 a
1B
b0 3
b0 `
b0 f
b10000001001000 b
bx .
bx d
bx )
bx 4
bx q
b1 k
b11100 j
b11100 ,
b11100 O
b11100 ;
b11100 l
b110 i
b100 ^
b1100111 _
b10011100 A
b10011100 T
b10011100 h
b10111000 #
b10111000 *
b10111000 -
b10111000 p
b10111000 F
b10111000 S
b10111000 W
b10111000 [
b1001110000110000000011100111 '
b1001110000110000000011100111 2
b1001110000110000000011100111 g
b1001110000110000000011100111 t
b1000 s
b10111100 @
b10111100 Z
b100100 =
b100100 J
b100100 X
b100000 &
b100000 +
b100000 1
b100000 N
b100000 P
1$
#17
0$
#18
b0 0
b0 e
b0 n
17
b0 .
b0 d
b0 )
b0 4
b0 q
b10111100 <
b10111100 L
b10111100 M
b10111000 5
b10111000 K
b10111000 \
b0 8
b0 Q
b0 V
b0 6
b0 Y
b0 c
0I
0H
1!
1>
09
0B
b1 3
b1 `
b1 f
b0 #
b0 *
b0 -
b0 p
b0 F
b0 S
b0 W
b0 [
b10000100000001 b
b0 k
b10100 "
b10100 (
b10100 /
b10100 r
b10100 :
b10100 U
b10100 m
b1101 j
b0 ,
b0 O
b0 ;
b0 l
b1010 i
b10 ]
b0 ^
b100011 _
b0 A
b0 T
b0 h
b110101010010000000100011 '
b110101010010000000100011 2
b110101010010000000100011 g
b110101010010000000100011 t
b101110 s
b10111000 @
b10111000 Z
b10111100 =
b10111100 J
b10111100 X
b10111000 &
b10111000 +
b10111000 1
b10111000 N
b10111000 P
1$
#19
0$
#20
b100 0
b100 e
b100 n
b100 6
b100 Y
b100 c
07
b100 #
b100 *
b100 -
b100 p
b100 F
b100 S
b100 W
b100 [
b100 8
b100 Q
b100 V
b11000000 5
b11000000 K
b11000000 \
b11000000 <
b11000000 L
b11000000 M
0!
0>
19
b0 3
b0 `
b0 f
b10000001000000 b
b1010 k
b0 "
b0 (
b0 /
b0 r
b0 :
b0 U
b0 m
b100 j
b0 ]
b10011 _
b100 A
b100 T
b100 h
b10001010000010100010011 '
b10001010000010100010011 2
b10001010000010100010011 g
b10001010000010100010011 t
b101111 s
b11000000 @
b11000000 Z
b11000000 =
b11000000 J
b11000000 X
b10111100 &
b10111100 +
b10111100 1
b10111100 N
b10111100 P
b10100 .
b10100 d
b10100 )
b10100 4
b10100 q
1$
#21
0$
#22
b0 8
b0 Q
b0 V
b11000100 0
b11000100 e
b11000100 n
b100100 5
b100100 K
b100100 \
b100100 <
b100100 L
b100100 M
1I
1H
1B
b10000001001000 b
b0 k
b0 j
b1 i
b1100111 _
b0 A
b0 T
b0 h
b1000000001100111 '
b1000000001100111 2
b1000000001100111 g
b1000000001100111 t
b110000 s
b11000100 6
b11000100 Y
b11000100 c
b11000000 @
b11000000 Z
b11000100 =
b11000100 J
b11000100 X
b11000000 &
b11000000 +
b11000000 1
b11000000 N
b11000000 P
b100 .
b100 d
b100 )
b100 4
b100 q
b100100 #
b100100 *
b100100 -
b100100 p
b100100 F
b100100 S
b100100 W
b100100 [
b100100 ,
b100100 O
b100100 ;
b100100 l
1$
#23
0$
#24
b11111111111111111111111111101100 0
b11111111111111111111111111101100 e
b11111111111111111111111111101100 n
b101000 <
b101000 L
b101000 M
b10000110000 5
b10000110000 K
b10000110000 \
b10100 8
b10100 Q
b10100 V
b11111111111111111111111111101100 6
b11111111111111111111111111101100 Y
b11111111111111111111111111101100 c
0I
0H
07
bx .
bx d
bx )
bx 4
bx q
0G
b10 E
b10 R
b10 a
0B
b111 3
b111 `
b111 f
b11111111111111111111111111101100 #
b11111111111111111111111111101100 *
b11111111111111111111111111101100 -
b11111111111111111111111111101100 p
b11111111111111111111111111101100 F
b11111111111111111111111111101100 S
b11111111111111111111111111101100 W
b11111111111111111111111111101100 [
b10001000111 b
b1101 k
b10100 "
b10100 (
b10100 /
b10100 r
b10100 :
b10100 U
b10100 m
b1100 j
b0 ,
b0 O
b0 ;
b0 l
b1011 i
b100000 ^
b110011 _
b10000001100 A
b10000001100 T
b10000001100 h
b1000000110001011000011010110011 '
b1000000110001011000011010110011 2
b1000000110001011000011010110011 g
b1000000110001011000011010110011 t
b1001 s
b10000110000 @
b10000110000 Z
b101000 =
b101000 J
b101000 X
b100100 &
b100100 +
b100100 1
b100100 N
b100100 P
1$
#25
0$
#26
b101000 0
b101000 e
b101000 n
b101000 6
b101000 Y
b101000 c
b0 8
b0 Q
b0 V
b101000 5
b101000 K
b101000 \
b101100 <
b101100 L
b101100 M
b101 .
b101 d
b101 )
b101 4
b101 q
b101000 #
b101000 *
b101000 -
b101000 p
b101000 F
b101000 S
b101000 W
b101000 [
b0 A
b0 T
b0 h
1G
b1010 E
b1010 R
b1010 a
b100 3
b100 `
b100 f
b11010001000100 b
b110 k
b0 "
b0 (
b0 /
b0 r
b0 :
b0 U
b0 m
b0 j
b0 i
b0 ^
b10111 _
b1100010111 '
b1100010111 2
b1100010111 g
b1100010111 t
b1010 s
b101000 @
b101000 Z
b101100 =
b101100 J
b101100 X
b101000 &
b101000 +
b101000 1
b101000 N
b101000 P
1$
#27
0$
#28
b110000 0
b110000 e
b110000 n
b10010000 8
b10010000 Q
b10010000 V
b110000 6
b110000 Y
b110000 c
b10111000 5
b10111000 K
b10111000 \
b10111000 <
b10111000 L
b10111000 M
1I
1H
b0 E
b0 R
b0 a
1B
b0 3
b0 `
b0 f
b10000001001000 b
bx .
bx d
bx )
bx 4
bx q
b1 k
b10000 j
b101000 ,
b101000 O
b101000 ;
b101000 l
b110 i
b100 ^
b1100111 _
b10010000 A
b10010000 T
b10010000 h
b10111000 #
b10111000 *
b10111000 -
b10111000 p
b10111000 F
b10111000 S
b10111000 W
b10111000 [
b1001000000110000000011100111 '
b1001000000110000000011100111 2
b1001000000110000000011100111 g
b1001000000110000000011100111 t
b1011 s
b10111100 @
b10111100 Z
b110000 =
b110000 J
b110000 X
b101100 &
b101100 +
b101100 1
b101100 N
b101100 P
1$
#29
0$
#30
b100 0
b100 e
b100 n
b10100 .
b10100 d
b10100 )
b10100 4
b10100 q
b10111100 <
b10111100 L
b10111100 M
b10111000 5
b10111000 K
b10111000 \
b0 8
b0 Q
b0 V
b100 6
b100 Y
b100 c
0I
0H
1!
1>
09
0B
b1 3
b1 `
b1 f
b100 #
b100 *
b100 -
b100 p
b100 F
b100 S
b100 W
b100 [
b10000100000001 b
b0 k
b11111111111111111111111111101100 "
b11111111111111111111111111101100 (
b11111111111111111111111111101100 /
b11111111111111111111111111101100 r
b11111111111111111111111111101100 :
b11111111111111111111111111101100 U
b11111111111111111111111111101100 m
b1101 j
b100 ,
b100 O
b100 ;
b100 l
b1010 i
b10 ]
b0 ^
b100011 _
b0 A
b0 T
b0 h
b110101010010000000100011 '
b110101010010000000100011 2
b110101010010000000100011 g
b110101010010000000100011 t
b101110 s
b10111000 @
b10111000 Z
b10111100 =
b10111100 J
b10111100 X
b10111000 &
b10111000 +
b10111000 1
b10111000 N
b10111000 P
1$
#31
0$
#32
b1000 0
b1000 e
b1000 n
b1000 6
b1000 Y
b1000 c
b1000 #
b1000 *
b1000 -
b1000 p
b1000 F
b1000 S
b1000 W
b1000 [
b100 8
b100 Q
b100 V
b11000000 5
b11000000 K
b11000000 \
b11000000 <
b11000000 L
b11000000 M
0!
0>
19
b0 3
b0 `
b0 f
b10000001000000 b
b1010 k
b0 "
b0 (
b0 /
b0 r
b0 :
b0 U
b0 m
b100 j
b0 ]
b10011 _
b100 A
b100 T
b100 h
b10001010000010100010011 '
b10001010000010100010011 2
b10001010000010100010011 g
b10001010000010100010011 t
b101111 s
b11000000 @
b11000000 Z
b11000000 =
b11000000 J
b11000000 X
b10111100 &
b10111100 +
b10111100 1
b10111100 N
b10111100 P
b101 .
b101 d
b101 )
b101 4
b101 q
1$
#33
0$
#34
b0 8
b0 Q
b0 V
b11000100 0
b11000100 e
b11000100 n
b110000 5
b110000 K
b110000 \
b110000 <
b110000 L
b110000 M
1I
1H
1B
b10000001001000 b
b0 k
b0 j
b1 i
b1100111 _
b0 A
b0 T
b0 h
b1000000001100111 '
b1000000001100111 2
b1000000001100111 g
b1000000001100111 t
b110000 s
b11000100 6
b11000100 Y
b11000100 c
b11000000 @
b11000000 Z
b11000100 =
b11000100 J
b11000100 X
b11000000 &
b11000000 +
b11000000 1
b11000000 N
b11000000 P
b111 .
b111 d
b111 )
b111 4
b111 q
b110000 #
b110000 *
b110000 -
b110000 p
b110000 F
b110000 S
b110000 W
b110000 [
b110000 ,
b110000 O
b110000 ;
b110000 l
1$
#35
0$
#36
b0 0
b0 e
b0 n
b110100 <
b110100 L
b110100 M
b111100 5
b111100 K
b111100 \
b10100 8
b10100 Q
b10100 V
b0 6
b0 Y
b0 c
0I
0H
17
b10100 .
b10100 d
b10100 )
b10100 4
b10100 q
0G
b1 E
b1 R
b1 a
0B
b111 3
b111 `
b111 f
b0 #
b0 *
b0 -
b0 p
b0 F
b0 S
b0 W
b0 [
b1001000111 b
b1101 k
b10100 "
b10100 (
b10100 /
b10100 r
b10100 :
b10100 U
b10100 m
b1100 j
b0 ,
b0 O
b0 ;
b0 l
b1011 i
b111 ]
b110011 _
b1100 A
b1100 T
b1100 h
b110001011111011010110011 '
b110001011111011010110011 2
b110001011111011010110011 g
b110001011111011010110011 t
b1100 s
b111100 @
b111100 Z
b110100 =
b110100 J
b110100 X
b110000 &
b110000 +
b110000 1
b110000 N
b110000 P
1$
#37
0$
